vidspinner/__init__.py
vidspinner/filters.py
vidspinner/vidspinner.py
vidspinner/builders/audio.py
vidspinner/builders/text.py
vidspinner-2.0.1.dist-info/LICENSE
vidspinner-2.0.1.dist-info/METADATA
vidspinner-2.0.1.dist-info/WHEEL
vidspinner-2.0.1.dist-info/top_level.txt
vidspinner-2.0.1.dist-info/RECORD
