Metadata-Version: 2.1
Name: vidspinner
Version: 2.0.1
Summary: VidSpinner is a Python library for easily creating unique versions of videos using filters, text, and audio effects.
Home-page: https://github.com/DedInc/vidspinner
Author: Maehdakvan
Author-email: visitanimation@google.com
Project-URL: Bug Tracker, https://github.com/DedInc/vidspinner/issues
Classifier: Programming Language :: Python :: 3
Classifier: License :: OSI Approved :: MIT License
Classifier: Operating System :: OS Independent
Requires-Python: >=3.6
License-File: LICENSE
